dst_annotations/__init__.py
dst_annotations/_annotations.py
dst_annotations/_annotations.pyi
dst_annotations/_inspect_annotations.py
dst_annotations/_jsoncompatible.py
dst_annotations/py.typed
dst_annotations-2021.2a0.dist-info/LICENSE
dst_annotations-2021.2a0.dist-info/METADATA
dst_annotations-2021.2a0.dist-info/WHEEL
dst_annotations-2021.2a0.dist-info/top_level.txt
dst_annotations-2021.2a0.dist-info/RECORD
